akaifire.py
akaifire-1.0.1.dist-info/LICENSE
akaifire-1.0.1.dist-info/METADATA
akaifire-1.0.1.dist-info/WHEEL
akaifire-1.0.1.dist-info/top_level.txt
akaifire-1.0.1.dist-info/RECORD
