Metadata-Version: 2.1
Name: akaifire
Version: 1.0.1
Summary: A interface library for the Akai FL Studio Fire
Author: Vykonn
License: GNU GENERAL PUBLIC LICENSE
Project-URL: Homepage, https://github.com/Vykonn/fire.py/
Requires-Python: >=3.11
License-File: LICENSE
Requires-Dist: python-rtmidi
